meeting_noter/__init__.py
meeting_noter/__main__.py
meeting_noter/cli.py
meeting_noter/config.py
meeting_noter/daemon.py
meeting_noter/meeting_detector.py
meeting_noter/mic_monitor.py
meeting_noter/update_checker.py
meeting_noter/audio/__init__.py
meeting_noter/audio/capture.py
meeting_noter/audio/encoder.py
meeting_noter/audio/system_audio.py
meeting_noter/install/__init__.py
meeting_noter/install/macos.py
meeting_noter/output/__init__.py
meeting_noter/output/favorites.py
meeting_noter/output/searcher.py
meeting_noter/output/writer.py
meeting_noter/resources/__init__.py
meeting_noter/resources/icon.icns
meeting_noter/resources/icon.png
meeting_noter/resources/icon_128.png
meeting_noter/resources/icon_16.png
meeting_noter/resources/icon_256.png
meeting_noter/resources/icon_32.png
meeting_noter/resources/icon_512.png
meeting_noter/resources/icon_64.png
meeting_noter/transcription/__init__.py
meeting_noter/transcription/engine.py
meeting_noter/transcription/live_transcription.py
meeting_noter-1.3.0.dist-info/METADATA
meeting_noter-1.3.0.dist-info/WHEEL
meeting_noter-1.3.0.dist-info/entry_points.txt
meeting_noter-1.3.0.dist-info/top_level.txt
meeting_noter-1.3.0.dist-info/RECORD
