Metadata-Version: 2.4
Name: meeting-noter
Version: 1.3.0
Summary: Offline meeting transcription for macOS with automatic meeting detection
Author: Victor
License: MIT
Project-URL: Homepage, https://github.com/tech4vision/meeting-noter
Project-URL: Repository, https://github.com/tech4vision/meeting-noter
Project-URL: Issues, https://github.com/tech4vision/meeting-noter/issues
Keywords: meeting,transcription,whisper,offline,speech-to-text,audio
Classifier: Development Status :: 3 - Alpha
Classifier: Environment :: Console
Classifier: Intended Audience :: End Users/Desktop
Classifier: License :: OSI Approved :: MIT License
Classifier: Operating System :: MacOS
Classifier: Programming Language :: Python :: 3
Classifier: Programming Language :: Python :: 3.9
Classifier: Programming Language :: Python :: 3.10
Classifier: Programming Language :: Python :: 3.11
Classifier: Programming Language :: Python :: 3.12
Classifier: Programming Language :: Python :: 3.13
Classifier: Topic :: Multimedia :: Sound/Audio :: Speech
Requires-Python: >=3.9
Requires-Dist: click>=8.0
Requires-Dist: sounddevice>=0.4.6
Requires-Dist: numpy>=1.24
Requires-Dist: faster-whisper>=1.0.0
Requires-Dist: imageio-ffmpeg>=0.4.9
Requires-Dist: pyobjc-framework-Cocoa>=9.0; sys_platform == "darwin"
Requires-Dist: pyobjc-framework-Quartz>=9.0; sys_platform == "darwin"
Requires-Dist: pyobjc-framework-ScreenCaptureKit>=9.0; sys_platform == "darwin"
Requires-Dist: pyobjc-framework-AVFoundation>=9.0; sys_platform == "darwin"
Requires-Dist: pyobjc-framework-CoreMedia>=9.0; sys_platform == "darwin"
Requires-Dist: pyobjc-framework-libdispatch>=9.0; sys_platform == "darwin"
Provides-Extra: offline
Requires-Dist: meeting-noter-models>=0.1.0; extra == "offline"
Provides-Extra: dev
Requires-Dist: pytest>=7.0; extra == "dev"
Requires-Dist: pytest-cov; extra == "dev"
Requires-Dist: pytest-mock; extra == "dev"
Requires-Dist: black; extra == "dev"
Requires-Dist: ruff; extra == "dev"
Requires-Dist: mypy; extra == "dev"
